{"4p1_10mini_1.mp4, put away all of our clean dishes": [[-1, -1]], "4p1_10mini_2.mp4, get our dinner dishes": [[-1, -1]], "4p1_10mini_2.mp4, reload the dishwasher": [[-1, -1]], "4p1_10mini_2.mp4, clean my sink out with some regular soap": [[30, 40], [40, 50], [50, 59.034]], "4p1_10mini_2.mp4, use the meyer ever mint scent dish soap": [[0, 10], [10, 20]], "4p1_10mini_3.mp4, clean off the counters": [[50, 54.7]], "4p1_10mini_5.mp4, give it a good vacuum": [[40, 50]], "4p1_10mini_5.mp4, throw pillows": [[0, 10], [10, 20], [40, 50], [50, 54.034]], "4p1_10mini_6.mp4, close our blinds": [[30, 40]], "4p1_1mini_1.mp4, get the dishes": [[-1, -1]], "4p1_1mini_13.mp4, wipe it down": [[-1, -1]], "4p1_1mini_13.mp4, use them": [[10, 19.834]], "4p1_1mini_13.mp4, wipe down our bathroom": [[-1, -1]], "4p1_1mini_16.mp4, tidy up a little bit": [[10, 20], [50, 56.167]], "4p1_1mini_16.mp4, go up to the playroom": [[50, 56.167]], "4p1_1mini_17.mp4, put those toys away": [[0, 10], [10, 20], [20, 30], [30, 40], [40, 50], [50, 57.2]], "4p1_1mini_17.mp4, get them these matching sheet sets": [[40, 50]], "4p1_1mini_17.mp4, put some new sheets on their bed": [[-1, -1]], "4p1_1mini_20.mp4, clean off": [[0, 10], [30, 40]], "4p1_1mini_21.mp4, vacuum then in the kids bathroom": [[0, 10], [10, 20]], "4p1_1mini_21.mp4, use a roomba in this house": [[0, 10], [10, 20], [20, 30]], "4p1_1mini_21.mp4, use our roomba upstairs today": [[10, 20]], "4p1_1mini_22.mp4, disinfect wipes": [[0, 10], [10, 20], [20, 30], [30, 40]], "4p1_1mini_22.mp4, look at this mirror": [[-1, -1]], "4p1_1mini_22.mp4, clean it": [[0, 10], [10, 20], [20, 30]], "4p1_1mini_22.mp4, combine the last of their laundry": [[-1, -1]], "4p1_1mini_23.mp4, vacuum all of our floors": [[40, 50]], "4p1_1mini_23.mp4, put into the wash machine": [[-1, -1]], "4p1_1mini_25.mp4, clean it": [[10, 20]], "4p1_1mini_3.mp4, wash that out": [[40, 50]], "4p1_1mini_3.mp4, add essential oils into my drain": [[0, 10], [10, 20], [20, 30]], "4p1_1mini_3.mp4, wipe down my counters today": [[0, 10], [10, 20], [20, 30], [30, 40], [40, 50]], "4p1_1mini_4.mp4, do a quick of my stove": [[50, 54.7]], "4p1_1mini_5.mp4, clean it": [[-1, -1]], "4p1_1mini_5.mp4, wipe it down with a wet rag with water": [[-1, -1]], "4p1_1mini_6.mp4, wipe down my bar stools": [[20, 30], [40, 50]], "4p1_1mini_8.mp4, vacuum our couch": [[20, 30], [30, 40], [40, 50]], "4p1_1mini_9.mp4, make our bed": [[40, 50], [50, 54.7]], "4p1_1mini_9.mp4, dust part off": [[0, 10], [20, 30], [30, 40]], "4p1_2mini_10.mp4, polish your stainless steel amazingly": [[0, 10], [10, 20], [30, 40]], "4p1_2mini_10.mp4, go into my living room": [[40, 50]], "4p1_2mini_12.mp4, try this vacuum": [[-1, -1]], "4p1_2mini_12.mp4, get my dyson": [[-1, -1]], "4p1_2mini_14.mp4, vacuum up": [[0, 10], [20, 24.834]], "4p1_2mini_16.mp4, take the garbage out": [[10, 20], [20, 30], [30, 40], [50, 55.3]], "4p1_2mini_3.mp4, get all the dirty dishes into the sink": [[30, 40], [50, 54.1]], "4p1_2mini_4.mp4, load our dishwasher at least once a day": [[10, 20]], "4p1_2mini_4.mp4, move on to the dishes": [[10, 20], [20, 30]], "4p1_2mini_4.mp4, load": [[10, 20]], "4p1_2mini_4.mp4, load it every single day": [[10, 20], [20, 30]], "4p1_2mini_5.mp4, clean out my sink": [[0, 10], [20, 30], [30, 40], [40, 50], [50, 54.834]], "4p1_2mini_5.mp4, add a few drops of essential oil into my drain": [[0, 10], [10, 20], [20, 30], [30, 40], [40, 50]], "4p1_2mini_5.mp4, clean it out": [[-1, -1]], "4p1_2mini_6.mp4, put away the dishes": [[-1, -1]], "4p1_2mini_6.mp4, get my dragon towel": [[0, 10], [10, 20]], "4p1_2mini_7.mp4, use them for several uses": [[0, 10], [30, 40], [40, 50]], "4p1_2mini_8.mp4, wipe it off": [[0, 10], [10, 20], [30, 40]], "4p1_2mini_8.mp4, do a big clean of my kitchen": [[30, 40], [40, 50]], "4p1_2mini_9.mp4, cover with a little bit of water": [[0, 10], [20, 30], [30, 40], [40, 50]], "4p1_2mini_9.mp4, use water": [[0, 10], [10, 20], [20, 30], [30, 40]], "4p1_2mini_9.mp4, rinse that same rag out with water": [[30, 40], [40, 50]], "4p1_2mini_9.mp4, polish your stainless steel": [[10, 20]], "4p1_2mini_9.mp4, wipe down the stove": [[0, 10], [10, 20], [30, 40]], "4p1_3mini_11.mp4, leave your couches": [[-1, -1]], "4p1_3mini_12.mp4, wipe it down": [[10, 20], [20, 30]], "4p1_3mini_13.mp4, pick up the books": [[0, 3.3659999999999997]], "4p1_3mini_14.mp4, use my dyson": [[-1, -1]], "4p1_3mini_15.mp4, add a little bit of essential oil to the pad": [[0, 10]], "4p1_3mini_17.mp4, got a couple bunches of flowers from the dollar tree": [[0, 10]], "4p1_3mini_17.mp4, set those in there": [[-1, -1]], "4p1_3mini_2.mp4, clear up the counters": [[10, 20]], "4p1_3mini_20.mp4, add a mirror into here": [[-1, -1]], "4p1_3mini_3.mp4, get any dishes in our sink": [[50, 57.567]], "4p1_3mini_4.mp4, add in some essential oil to my sink": [[0, 10], [10, 20], [20, 30], [40, 50]], "4p1_3mini_4.mp4, use dish meyers": [[0, 10]], "4p1_3mini_5.mp4, use my favorite cleaner": [[10, 20], [30, 40], [40, 50]], "4p1_3mini_5.mp4, wipe down my counters": [[20, 30]], "4p1_3mini_5.mp4, wipe down my barstools": [[20, 30]], "4p1_3mini_7.mp4, clean our stainless steel": [[0, 10], [10, 20], [20, 30], [30, 40]], "4p1_3mini_8.mp4, wipe down": [[0, 10], [20, 30]], "4p1_4mini_10.mp4, pick up a few of those things": [[10, 20]], "4p1_4mini_10.mp4, throw pillows on the couch": [[10, 20], [30, 40], [50, 58.034]], "4p1_4mini_11.mp4, clean up the toy room": [[0, 10], [10, 20], [20, 30]], "4p1_4mini_11.mp4, take all their toys upstairs": [[0, 10], [10, 20], [20, 30]], "4p1_4mini_11.mp4, clean for them": [[0, 10], [10, 20], [20, 30]], "4p1_4mini_12.mp4, sort out the rest of the toys from the toy bin": [[30, 40]], "4p1_4mini_12.mp4, clean up": [[-1, -1]], "4p1_4mini_12.mp4, clean up all of their legos": [[0, 10], [10, 20], [30, 40]], "4p1_4mini_14.mp4, mop the floors": [[0, 10], [10, 20], [40, 50], [50, 56.034]], "4p1_4mini_15.mp4, add a little bit of essential oil onto them": [[0, 10], [10, 20], [20, 30]], "4p1_4mini_15.mp4, dampen the clock a little bit": [[-1, -1]], "4p1_4mini_15.mp4, mop your floors with it": [[-1, -1]], "4p1_4mini_4.mp4, use the meyers peppermint scent": [[20, 30], [40, 50], [50, 56.367]], "4p1_4mini_5.mp4, put back": [[30, 40]], "4p1_4mini_5.mp4, add a few drops of essential oil into it": [[0, 10], [10, 20], [20, 30], [40, 50], [50, 56.7]], "4p1_4mini_6.mp4, wipe down everything from our counters": [[40, 50]], "4p1_4mini_6.mp4, put all of the dry dishes": [[30, 40], [40, 50]], "4p1_4mini_8.mp4, add about a tablespoon": [[20, 30]], "4p1_4mini_8.mp4, fill the rest up with water": [[0, 10], [20, 30]], "4p1_4mini_8.mp4, wipe down our stove": [[20, 30]], "4p1_4mini_8.mp4, make the cal drake concentrate cleaner": [[0, 10], [10, 20], [20, 30]], "4p1_4mini_8.mp4, wipe it down": [[20, 30]], "4p1_4mini_9.mp4, wipe them down with a wet rag with water": [[0, 10], [10, 20], [20, 30], [40, 50], [50, 58.367]], "4p1_5mini_1.mp4, take my sheets off": [[10, 20]], "4p1_5mini_1.mp4, chang out my sheets now": [[10, 20]], "4p1_5mini_3.mp4, start to dry dust our furniture": [[0, 10], [30, 40], [40, 50], [50, 56.967]], "4p1_5mini_3.mp4, wipe them down at least once a week": [[40, 50], [50, 56.967]], "4p1_5mini_3.mp4, wipe those down": [[10, 20], [20, 30], [30, 40], [40, 50], [50, 56.967]], "4p1_5mini_3.mp4, wipe them down about once a week": [[50, 56.967]], "4p1_5mini_5.mp4, use the method antibacterial bathroom cleaner": [[0, 10], [20, 30], [40, 50]], "4p1_5mini_5.mp4, fill up my diffuser": [[10, 20], [20, 30]], "4p1_5mini_5.mp4, use this on all of my bathroom": [[30, 40]], "4p1_5mini_6.mp4, wipe down my countertops": [[40, 50], [50, 58.634]], "4p1_5mini_6.mp4, rinse out with water": [[-1, -1]], "4p1_5mini_6.mp4, use my dollar tree cloth": [[10, 20], [20, 30], [30, 40], [40, 50]], "4p1_5mini_6.mp4, wipe down the mirror": [[0, 10], [10, 20], [50, 58.634]], "4p1_5mini_6.mp4, clean it perfectly with water": [[0, 10], [10, 20], [50, 58.634]], "4p1_5mini_6.mp4, wipe the entire mirror down with the water": [[0, 10], [10, 20], [50, 58.634]], "4p1_5mini_7.mp4, wipe this down at multiple times a week": [[0, 10], [10, 20], [20, 30], [30, 40], [40, 50]], "4p1_5mini_7.mp4, feed my toilet": [[30, 40], [40, 50], [50, 57.767]], "4p1_5mini_7.mp4, use the method toilet bowl cleaner": [[30, 40], [50, 57.767]], "4p1_5mini_8.mp4, use our dyson vacuums": [[10, 20]], "4p1_5mini_8.mp4, clean the toilet": [[10, 20]], "4p1_5mini_8.mp4, vacuum our room": [[30, 40]], "4p1_5mini_9.mp4, do a quick vacuum through there": [[0, 10], [10, 20]], "4p1_5mini_9.mp4, mop our tile floors with my steam": [[0, 10]], "4p1_6mini_1.mp4, put the mattress underneath noah bed his bed": [[10, 20], [20, 30], [40, 50], [50, 53.034]], "4p1_6mini_1.mp4, take off the bedding from our guest bed": [[0, 10], [10, 20], [20, 30], [40, 50]], "4p1_6mini_1.mp4, clean up our playroom": [[20, 30], [30, 40], [40, 50], [50, 53.034]], "4p1_6mini_3.mp4, put in one part dish soap to one part of white vinegar mix it up": [[0, 10], [40, 50], [50, 54.767]], "4p1_6mini_3.mp4, spray down very liberally": [[0, 10]], "4p1_6mini_4.mp4, clean our toilets": [[0, 10]], "4p1_6mini_4.mp4, wipe them down almost every day": [[-1, -1]], "4p1_6mini_6.mp4, use the method glass": [[10, 20], [20, 30], [30, 40]], "4p1_6mini_6.mp4, move back into the shower": [[30, 40]], "4p1_6mini_6.mp4, clean up": [[50, 57.7]], "4p1_6mini_6.mp4, mirror clean": [[30, 40], [50, 57.7]], "4p1_6mini_7.mp4, dump it on the walls": [[40, 50]], "4p1_6mini_7.mp4, rinse it off with water": [[20, 30], [30, 40], [40, 50]], "4p1_6mini_8.mp4, do all my other cleaning": [[0, 10], [10, 20], [20, 30], [30, 40], [40, 50], [50, 55.834]], "4p1_6mini_8.mp4, fill it up with water": [[50, 55.834]], "4p1_6mini_8.mp4, mop if": [[0, 10], [10, 20], [20, 30], [50, 55.834]], "4p1_6mini_8.mp4, vacuum the boys room": [[-1, -1]], "4p1_8mini_1.mp4, put some things away on our counters": [[-1, -1]], "4p1_8mini_1.mp4, tidy up before luke": [[-1, -1]], "4p1_8mini_1.mp4, put away our pineapple juice": [[30, 40]], "4p1_8mini_1.mp4, clean around the house": [[0, 10], [10, 20], [20, 30], [40, 50], [50, 52.7]], "4p1_8mini_2.mp4, wash out my sink": [[20, 30], [30, 40]], "4p1_8mini_2.mp4, clean up": [[-1, -1]], "4p1_8mini_2.mp4, use my dish soap": [[-1, -1]], "4p1_8mini_2.mp4, load up the rest of the dishes into the dishwasher": [[-1, -1]], "4p1_8mini_2.mp4, wash any dishes": [[-1, -1]], "4p1_8mini_3.mp4, add some essential oils into my sink": [[-1, -1]], "4p1_8mini_3.mp4, see a nice clean sink": [[-1, -1]], "4p1_8mini_4.mp4, use the same spray here": [[0, 10]], "4p1_8mini_4.mp4, wipe down my table": [[10, 20], [20, 30], [30, 40], [50, 57.3]], "4p1_8mini_4.mp4, clear off the counter": [[50, 57.3]], "4p1_8mini_6.mp4, clean off": [[-1, -1]], "4p1_8mini_6.mp4, put things away": [[0, 10], [30, 40]], "4p1_8mini_6.mp4, vacuum at least once a day usually twice a day one": [[30, 40]], "4p1_8mini_6.mp4, vacuum": [[0, 10]], "4p1_8mini_6.mp4, tidy it up": [[0, 10], [30, 40]], "4p1_8mini_8.mp4, tidy up the main living space": [[10, 20], [30, 40]], "4p1_8mini_8.mp4, get everything vacuum": [[10, 20]]}